{
  "parents": [],
  "children": [],
  "partyRequests": [
    {
      "description": "Son's 6th Birthday Party",
      "parentName": "Andrew",
      "childName": "Ethan",
      "numberOfChildren": "6",
      "address": "1111 Hello street",
      "date": "2021-07-25",
      "id": 3
    },
    {
      "description": "Graduation Party",
      "parentName": "Paul",
      "childName": "Alesia",
      "numberOfChildren": "200",
      "address": "geraldine",
      "date": "2021-05-21",
      "id": 4
    }
  ],
  "chronologicalPartyOrder": [],
  "clowns": [
    {
      "id": 1,
      "name": "Buttons"
    },
    {
      "id": 2,
      "name": "Lollipop"
    }
  ],
  "completions": [
    {
      "requestId": "4",
      "clownId": "1",
      "date": "5/12/2021",
      "id": 1
    }
  ]
}